{"yearlyData":[{"year":1999,"housingCost":71875,"income":15383,"mortgagePeriod":21,"ratio":4.67},{"year":2000,"housingCost":82500,"income":18260,"mortgagePeriod":20,"ratio":4.52},{"year":2001,"housingCost":98000,"income":19402,"mortgagePeriod":23,"ratio":5.05},{"year":2002,"housingCost":118749,"income":20545,"mortgagePeriod":29,"ratio":5.78},{"year":2003,"housingCost":146242,"income":21688,"mortgagePeriod":37,"ratio":6.74},{"year":2004,"housingCost":168062,"income":22678,"mortgagePeriod":45,"ratio":7.41},{"year":2005,"housingCost":186375,"income":22231,"mortgagePeriod":61,"ratio":8.38},{"year":2006,"housingCost":193431,"income":22710,"mortgagePeriod":64,"ratio":8.52},{"year":2007,"housingCost":203118,"income":19599,"mortgagePeriod":833,"ratio":10.36},{"year":2008,"housingCost":216250,"income":24183,"mortgagePeriod":76,"ratio":8.94},{"year":2009,"housingCost":203562,"income":25115,"mortgagePeriod":56,"ratio":8.11},{"year":2010,"housingCost":196248,"income":24884,"mortgagePeriod":52,"ratio":7.89},{"year":2011,"housingCost":209500,"income":28209,"mortgagePeriod":45,"ratio":7.43},{"year":2012,"housingCost":206987,"income":25771,"mortgagePeriod":54,"ratio":8.03},{"year":2013,"housingCost":212125,"income":25483,"mortgagePeriod":60,"ratio":8.32},{"year":2014,"housingCost":222743,"income":25195,"mortgagePeriod":73,"ratio":8.84},{"year":2015,"housingCost":242748,"income":24907,"mortgagePeriod":130,"ratio":9.75}],"LADid":"E07000074","LADname":"Maldon"}