{"yearlyData":[{"currentYear":1998,"housingCost":46000,"income":14156,"mortgagePeriod":13,"ratio":3.25},{"currentYear":1999,"housingCost":48625,"income":15707,"mortgagePeriod":12,"ratio":3.1},{"currentYear":2000,"housingCost":47500,"income":16884,"mortgagePeriod":11,"ratio":2.81},{"currentYear":2001,"housingCost":49375,"income":18174,"mortgagePeriod":10,"ratio":2.72},{"currentYear":2002,"housingCost":58562,"income":18282,"mortgagePeriod":13,"ratio":3.2},{"currentYear":2003,"housingCost":79487,"income":18612,"mortgagePeriod":18,"ratio":4.27},{"currentYear":2004,"housingCost":95975,"income":19492,"mortgagePeriod":22,"ratio":4.92},{"currentYear":2005,"housingCost":108250,"income":20473,"mortgagePeriod":25,"ratio":5.29},{"currentYear":2006,"housingCost":118875,"income":21749,"mortgagePeriod":26,"ratio":5.47},{"currentYear":2007,"housingCost":124362,"income":22606,"mortgagePeriod":26,"ratio":5.5},{"currentYear":2008,"housingCost":118537,"income":22058,"mortgagePeriod":25,"ratio":5.37},{"currentYear":2009,"housingCost":120000,"income":22950,"mortgagePeriod":24,"ratio":5.23},{"currentYear":2010,"housingCost":119412,"income":22564,"mortgagePeriod":25,"ratio":5.29},{"currentYear":2011,"housingCost":118625,"income":22571,"mortgagePeriod":25,"ratio":5.26},{"currentYear":2012,"housingCost":120275,"income":24116,"mortgagePeriod":23,"ratio":4.99},{"currentYear":2013,"housingCost":121500,"income":23592,"mortgagePeriod":24,"ratio":5.15},{"currentYear":2014,"housingCost":120437,"income":23455,"mortgagePeriod":24,"ratio":5.13}],"LADid":"E07000028","LADname":"Carlisle"}