{"yearlyData":[{"currentYear":1999,"housingCost":79437,"income":14907,"mortgagePeriod":25,"ratio":5.33},{"currentYear":2000,"housingCost":91874,"income":15929,"mortgagePeriod":28,"ratio":5.77},{"currentYear":2001,"housingCost":108875,"income":16991,"mortgagePeriod":34,"ratio":6.41},{"currentYear":2002,"housingCost":126500,"income":16879,"mortgagePeriod":46,"ratio":7.49},{"currentYear":2003,"housingCost":157112,"income":18735,"mortgagePeriod":61,"ratio":8.39},{"currentYear":2004,"housingCost":183500,"income":19561,"mortgagePeriod":95,"ratio":9.38},{"currentYear":2005,"housingCost":202875,"income":20653,"mortgagePeriod":147,"ratio":9.82},{"currentYear":2006,"housingCost":211487,"income":22589,"mortgagePeriod":94,"ratio":9.36},{"currentYear":2007,"housingCost":226750,"income":21594,"mortgagePeriod":833,"ratio":10.5},{"currentYear":2008,"housingCost":237625,"income":23823,"mortgagePeriod":833,"ratio":9.97},{"currentYear":2009,"housingCost":223687,"income":23554,"mortgagePeriod":103,"ratio":9.5},{"currentYear":2010,"housingCost":222487,"income":22972,"mortgagePeriod":121,"ratio":9.69},{"currentYear":2011,"housingCost":232937,"income":24229,"mortgagePeriod":113,"ratio":9.61},{"currentYear":2012,"housingCost":234875,"income":24999,"mortgagePeriod":96,"ratio":9.4},{"currentYear":2013,"housingCost":232500,"income":25910,"mortgagePeriod":77,"ratio":8.97},{"currentYear":2014,"housingCost":233250,"income":25121,"mortgagePeriod":90,"ratio":9.29},{"currentYear":2015,"housingCost":246625,"income":24810,"mortgagePeriod":833,"ratio":9.94}],"LADid":"E07000052","LADname":"West Dorset"}