{"yearlyData":[{"currentYear":1998,"housingCost":145875,"income":21075,"mortgagePeriod":39,"ratio":6.92},{"currentYear":1999,"housingCost":171687,"income":23400,"mortgagePeriod":44,"ratio":7.34},{"currentYear":2000,"housingCost":201668,"income":23963,"mortgagePeriod":62,"ratio":8.42},{"currentYear":2001,"housingCost":220750,"income":24836,"mortgagePeriod":74,"ratio":8.89},{"currentYear":2002,"housingCost":246987,"income":25033,"mortgagePeriod":163,"ratio":9.87},{"currentYear":2003,"housingCost":260000,"income":26182,"mortgagePeriod":231,"ratio":9.93},{"currentYear":2004,"housingCost":283000,"income":30339,"mortgagePeriod":92,"ratio":9.33},{"currentYear":2005,"housingCost":304312,"income":28316,"mortgagePeriod":833,"ratio":10.75},{"currentYear":2006,"housingCost":334300,"income":31541,"mortgagePeriod":833,"ratio":10.6},{"currentYear":2007,"housingCost":366625,"income":30165,"mortgagePeriod":833,"ratio":12.15},{"currentYear":2008,"housingCost":364250,"income":30593,"mortgagePeriod":833,"ratio":11.91},{"currentYear":2009,"housingCost":373000,"income":31022,"mortgagePeriod":833,"ratio":12.02},{"currentYear":2010,"housingCost":389125,"income":31635,"mortgagePeriod":833,"ratio":12.3},{"currentYear":2011,"housingCost":393987,"income":32249,"mortgagePeriod":833,"ratio":12.22},{"currentYear":2012,"housingCost":415000,"income":32295,"mortgagePeriod":833,"ratio":12.85},{"currentYear":2013,"housingCost":439250,"income":31504,"mortgagePeriod":833,"ratio":13.94},{"currentYear":2014,"housingCost":471250,"income":33555,"mortgagePeriod":833,"ratio":14.04}],"LADid":"E07000207","LADname":"Elmbridge"}