{"yearlyData":[{"currentYear":1999,"housingCost":96750,"income":20314,"mortgagePeriod":21,"ratio":4.76},{"currentYear":2000,"housingCost":114250,"income":19265,"mortgagePeriod":30,"ratio":5.93},{"currentYear":2001,"housingCost":128625,"income":21748,"mortgagePeriod":30,"ratio":5.91},{"currentYear":2002,"housingCost":146047,"income":22524,"mortgagePeriod":35,"ratio":6.48},{"currentYear":2003,"housingCost":169625,"income":22103,"mortgagePeriod":49,"ratio":7.67},{"currentYear":2004,"housingCost":189862,"income":25081,"mortgagePeriod":47,"ratio":7.57},{"currentYear":2005,"housingCost":207500,"income":23173,"mortgagePeriod":76,"ratio":8.95},{"currentYear":2006,"housingCost":212812,"income":22986,"mortgagePeriod":89,"ratio":9.26},{"currentYear":2007,"housingCost":225875,"income":23604,"mortgagePeriod":109,"ratio":9.57},{"currentYear":2008,"housingCost":234000,"income":24390,"mortgagePeriod":111,"ratio":9.59},{"currentYear":2009,"housingCost":220500,"income":25559,"mortgagePeriod":67,"ratio":8.63},{"currentYear":2010,"housingCost":225812,"income":25262,"mortgagePeriod":76,"ratio":8.94},{"currentYear":2011,"housingCost":237487,"income":25730,"mortgagePeriod":87,"ratio":9.23},{"currentYear":2012,"housingCost":237375,"income":26720,"mortgagePeriod":74,"ratio":8.88},{"currentYear":2013,"housingCost":242112,"income":26172,"mortgagePeriod":88,"ratio":9.25},{"currentYear":2014,"housingCost":244875,"income":27145,"mortgagePeriod":79,"ratio":9.02},{"currentYear":2015,"housingCost":271181,"income":28119,"mortgagePeriod":116,"ratio":9.64}],"LADid":"E07000181","LADname":"West Oxfordshire"}