{"yearlyData":[{"year":1999,"housingCost":55206,"income":16637,"mortgagePeriod":13,"ratio":3.32},{"year":2000,"housingCost":58362,"income":16988,"mortgagePeriod":14,"ratio":3.44},{"year":2001,"housingCost":66487,"income":17023,"mortgagePeriod":16,"ratio":3.91},{"year":2002,"housingCost":75737,"income":18051,"mortgagePeriod":18,"ratio":4.2},{"year":2003,"housingCost":89350,"income":19953,"mortgagePeriod":19,"ratio":4.48},{"year":2004,"housingCost":110375,"income":19337,"mortgagePeriod":28,"ratio":5.71},{"year":2005,"housingCost":125250,"income":21312,"mortgagePeriod":29,"ratio":5.88},{"year":2006,"housingCost":129250,"income":21668,"mortgagePeriod":30,"ratio":5.97},{"year":2007,"housingCost":136812,"income":22240,"mortgagePeriod":32,"ratio":6.15},{"year":2008,"housingCost":138462,"income":22813,"mortgagePeriod":31,"ratio":6.07},{"year":2009,"housingCost":132956,"income":21512,"mortgagePeriod":32,"ratio":6.18},{"year":2010,"housingCost":133375,"income":21533,"mortgagePeriod":32,"ratio":6.19},{"year":2011,"housingCost":132800,"income":21853,"mortgagePeriod":31,"ratio":6.08},{"year":2012,"housingCost":129750,"income":22464,"mortgagePeriod":28,"ratio":5.78},{"year":2013,"housingCost":131737,"income":22096,"mortgagePeriod":30,"ratio":5.96},{"year":2014,"housingCost":138818,"income":23038,"mortgagePeriod":31,"ratio":6.03},{"year":2015,"housingCost":145493,"income":22843,"mortgagePeriod":34,"ratio":6.37}],"LADid":"E07000199","LADname":"Tamworth"}