{"yearlyData":[{"year":1999,"housingCost":"Null","income":17480,"mortgagePeriod":"Null","ratio":"Null"},{"year":2000,"housingCost":"Null","income":18953,"mortgagePeriod":"Null","ratio":"Null"},{"year":2001,"housingCost":"Null","income":17699,"mortgagePeriod":"Null","ratio":"Null"},{"year":2002,"housingCost":"Null","income":18250,"mortgagePeriod":"Null","ratio":"Null"},{"year":2003,"housingCost":56573,"income":19307,"mortgagePeriod":11,"ratio":2.93},{"year":2004,"housingCost":68675,"income":20629,"mortgagePeriod":13,"ratio":3.33},{"year":2005,"housingCost":77874,"income":21891,"mortgagePeriod":14,"ratio":3.56},{"year":2006,"housingCost":91250,"income":22751,"mortgagePeriod":17,"ratio":4.01},{"year":2007,"housingCost":109146,"income":23003,"mortgagePeriod":21,"ratio":4.74},{"year":2008,"housingCost":94250,"income":24069,"mortgagePeriod":16,"ratio":3.92},{"year":2009,"housingCost":91280,"income":23926,"mortgagePeriod":16,"ratio":3.82},{"year":2010,"housingCost":91875,"income":24125,"mortgagePeriod":16,"ratio":3.81},{"year":2011,"housingCost":93906,"income":24085,"mortgagePeriod":16,"ratio":3.9},{"year":2012,"housingCost":85720,"income":24928,"mortgagePeriod":14,"ratio":3.44},{"year":2013,"housingCost":82815,"income":25313,"mortgagePeriod":13,"ratio":3.27},{"year":2014,"housingCost":89062,"income":25841,"mortgagePeriod":14,"ratio":3.45},{"year":2015,"housingCost":96250,"income":25045,"mortgagePeriod":16,"ratio":3.84}],"LADid":"S12000008","LADname":"East Ayrshire"}