{"1998":{"housingCost":0,"income":16914,"mortagePeriod":0,"ratio":0},"1999":{"housingCost":0,"income":18029,"mortagePeriod":0,"ratio":0},"2000":{"housingCost":0,"income":18610,"mortagePeriod":0,"ratio":0},"2001":{"housingCost":0,"income":19167,"mortagePeriod":0,"ratio":0},"2002":{"housingCost":79500,"income":19799,"mortagePeriod":17,"ratio":4.015354310823779},"2003":{"housingCost":92062,"income":20598,"mortagePeriod":19,"ratio":4.469463054665502},"2004":{"housingCost":102000,"income":21312,"mortagePeriod":21,"ratio":4.786036036036036},"2005":{"housingCost":117500,"income":22373,"mortagePeriod":25,"ratio":5.251866088588924},"2006":{"housingCost":129625,"income":23098,"mortagePeriod":27,"ratio":5.61195774525933},"2007":{"housingCost":126132,"income":24105,"mortagePeriod":24,"ratio":5.232607342874922},"2008":{"housingCost":126623,"income":24993,"mortagePeriod":23,"ratio":5.066338574800945},"2009":{"housingCost":126998,"income":25205,"mortagePeriod":23,"ratio":5.038603451696092},"2010":{"housingCost":129500,"income":25291,"mortagePeriod":24,"ratio":5.120398560752837},"2011":{"housingCost":125753,"income":25780,"mortagePeriod":22,"ratio":4.877928626842514},"2012":{"housingCost":129500,"income":26489,"mortagePeriod":22,"ratio":4.888821775076447},"2013":{"housingCost":138634,"income":27038,"mortagePeriod":24,"ratio":5.127376285228197},"2014":{"housingCost":139639,"income":27710,"mortagePeriod":23,"ratio":5.039299891735835},"ID":"S92000003","LAD":"Scotland"}